[
    {
        "ranking": "1",
        "title": "Minnalvala",
        "artist": "Sid Sriram & Sithara Krishnakumar",
        "image": "https://lh3.googleusercontent.com/m-KIBZD67XkdjorOjb-Nf5MZQIcVnxU9C8ZLdFRxlhChIvBBNtyZHCfh0tHSatqnYvrSOOfyczu2XoFk=w180-h180-l90-rj",
        "prev": "1",
        "streak": "12",
        "streams": "375,964",
        "youtubeID": "izbydia9jz4"
    },
    {
        "ranking": "2",
        "title": "Muththa Mazhai (Live)",
        "artist": "A. R. Rahman & Dhee & Siva Ananth",
        "image": "https://lh3.googleusercontent.com/r9UzClLbmwsKwUzWEvIAgDj9aE49Sp6SidhJCa9gqLJ1TZNYUiqBJeAENztF8jihbFu9weyV4zMocdMqxA=w180-h180-l90-rj",
        "prev": "2",
        "streak": "7",
        "streams": "320,492",
        "youtubeID": "1d08HAQDqpU"
    },
    {
        "ranking": "3",
        "title": "خطية | Khtaya",
        "artist": "Bessan Ismail & Fouad Jned",
        "image": "https://lh3.googleusercontent.com/kRTkPtK4ikme4wr4Br-hWp_Yd1YZDBRTPfiwmMq505xk_m5oQ47KlDGcHEZI6z22hs1IdDULkcKyWEs=w180-h180-l90-rj",
        "prev": "4",
        "streak": "9",
        "streams": "255,861",
        "youtubeID": "LsyviHWrNB4"
    },
    {
        "ranking": "4",
        "title": "Sapphire",
        "artist": "Ed Sheeran",
        "image": "https://lh3.googleusercontent.com/gFoL_IiMW-6i63a8FlitjPneJ0Usq1xNj1ZVE6sNgXsZimA3axRCuVCQKvj_300QDfkAQsQfMVguFdE=w180-h180-l90-rj",
        "prev": "3",
        "streak": "5",
        "streams": "242,115",
        "youtubeID": "JgDNFQ2RaLQ"
    },
    {
        "ranking": "5",
        "title": "أحلى رسمه",
        "artist": "Fadel Chaker",
        "image": "https://lh3.googleusercontent.com/FqIP498aQK3LHPd68s8tX6xVtI3R_Mr-tbcQrJvReeP07uCLE9MVXZ_znar_4Gf5Oraci3APTc7pYMCy=w180-h180-l90-rj",
        "prev": "6",
        "streak": "12",
        "streams": "229,275",
        "youtubeID": "VkH3aMIWntw"
    },
    {
        "ranking": "6",
        "title": "Jhol",
        "artist": "Maanu & Annural Khalid",
        "image": "https://lh3.googleusercontent.com/GP9v2CnfMkE8wF3zy1An4FECREeFYy-6Y4iS2OwvISYnOTF09e6sSfD5XYuUjgaiczGvliqbycu3Yp27=w180-h180-l90-rj",
        "prev": "7",
        "streak": "39",
        "streams": "202,086",
        "youtubeID": "-2RAq5o5pwc"
    },
    {
        "ranking": "7",
        "title": "Shaky",
        "artist": "Sanju Rathod & G-Spark",
        "image": "https://lh3.googleusercontent.com/j6r-vjZ4tY2AlScNLSCshTdvZ4mGxga2VlTRCupta2SbEjP5WISoN0Ef0Xqf0OoN-odlnrAA1ia_l4M=w180-h180-l90-rj",
        "prev": "9",
        "streak": "7",
        "streams": "197,316",
        "youtubeID": "sUf2PtEZris"
    },
    {
        "ranking": "8",
        "title": "كيفك ع فراقي",
        "artist": "Mohamed Chaker & Fadel Chaker",
        "image": "https://lh3.googleusercontent.com/RSzqApTanYWi3RtEtMUtfaa_yiM_OEob5qphBtLMh_TjrFuYWUWso1LM-JqmozWF4fYn8Xg-tIuOJeA=w180-h180-l90-rj",
        "prev": "-",
        "streak": "1",
        "streams": "195,888",
        "youtubeID": "m5IWI6xFRms"
    },
    {
        "ranking": "9",
        "title": "Pal Pal",
        "artist": "Afusic & AliSoomroMusic",
        "image": "https://lh3.googleusercontent.com/GoaPJH-3iAmrBnIQrELduHeCjzRHy45rHb3AbNEncitKZGaZQwMkeu5sYDyvW5VgvpPZSD_VsAjmEOv9=w180-h180-l90-rj",
        "prev": "10",
        "streak": "15",
        "streams": "184,950",
        "youtubeID": "8of5w7RgcTc"
    },
    {
        "ranking": "10",
        "title": "Khatfoony (feat. Jana Diab)",
        "artist": "Amr Diab & Orange",
        "image": "https://lh3.googleusercontent.com/h0kdl-YLc1Cv1433qTa76P_LC9hIeWo6B2styg7DeurhZhYWFUOl9bMboKnMWOJ8Ss8rxcX1TP9xK5k=w180-h180-l90-rj",
        "prev": "-",
        "streak": "1",
        "streams": "183,506",
        "youtubeID": "QvDb3YGYfcs"
    },
    {
        "ranking": "11",
        "title": "APT.",
        "artist": "ROSÉ & Bruno Mars",
        "image": "https://lh3.googleusercontent.com/-MtYkhdYuOvj8YWHA4afh-OUYMYHNpBpkk047QgGAxLJMLE570Pj0-LQjA2PW1ltedqTusKOjzXvuS8=w180-h180-l90-rj",
        "prev": "8",
        "streak": "38",
        "streams": "180,777",
        "youtubeID": "ekr2nIex040"
    },
    {
        "ranking": "12",
        "title": "Aaj Ki Raat",
        "artist": "Madhubanti Bagchi & Divya Kumar & Sachin-Jigar",
        "image": "https://lh3.googleusercontent.com/UAA-RHT1goYnsJDghUnbVrkKOwLuMgXWryI7ezcqQD6XAEusG261rgYPdnYh698cfuw6-YTI_jk9t6TRnw=w180-h180-l90-rj",
        "prev": "12",
        "streak": "51",
        "streams": "179,786",
        "youtubeID": "roz9sXFkTuE"
    },
    {
        "ranking": "13",
        "title": "Chirapunji",
        "artist": "Nihal Sadiq & Hanan Shaah",
        "image": "https://lh3.googleusercontent.com/Lxc6MKahEPklR4IpU9ok7GuAxh1OfE0S-ZMYobYvBrxlRtwJ1Hz0OwpylUpGYaUDJcatC41LAuTwe6B7Ew=w180-h180-l90-rj",
        "prev": "5",
        "streak": "4",
        "streams": "174,833",
        "youtubeID": "dDRj50HRkXI"
    },
    {
        "ranking": "14",
        "title": "Maleket Gamal El Kon",
        "artist": "Tamer Hosny & Al Shami",
        "image": "https://lh3.googleusercontent.com/ai5x51-GK4ZO5_1j-ymHlW0_VrbM0JcyANNVMltiCc4ET3tZUwZcsXmrTYBcLmyf0zjuWuQk5kT5IXqUzQ=w180-h180-l90-rj",
        "prev": "14",
        "streak": "7",
        "streams": "166,857",
        "youtubeID": "mUC-Um5Jauw"
    },
    {
        "ranking": "15",
        "title": "Die With A Smile",
        "artist": "Lady Gaga & Bruno Mars",
        "image": "https://lh3.googleusercontent.com/RFK4wHeGqwI3DndbARbRJB21IC0TcmqnrlyjxYK7T-nC8wlIVbfxNaCIFKNvSpchDKmYyVLe1RN36w=w180-h180-l90-rj",
        "prev": "13",
        "streak": "47",
        "streams": "154,757",
        "youtubeID": "kPa7bsKwL-c"
    },
    {
        "ranking": "16",
        "title": "Golden",
        "artist": "HUNTR/X & EJAE & AUDREY NUNA & REI AMI & KPop Demon Hunters Cast",
        "image": "https://lh3.googleusercontent.com/1U-1pXbvkpvGXGUIFs5m6RXz4Fmdvqo1zzQw8eY7b4G9iwpE6vaRclt8Ov5CS8ldROIQGu2InpGuSJSW=w180-h180-l90-rj",
        "prev": "24",
        "streak": "3",
        "streams": "145,737",
        "youtubeID": "yebNIHKAC4A"
    },
    {
        "ranking": "17",
        "title": "Laal Pari",
        "artist": "Yo Yo Honey Singh & Simar Kaur",
        "image": "https://lh3.googleusercontent.com/IlB_k-DBSPYz6lYVHNMn_MLKCxZk09Le4XopHv9SSyw9HSRiyO25W5nrbcBW9c8dohWufRlg7e5MG_haMg=w180-h180-l90-rj",
        "prev": "17",
        "streak": "10",
        "streams": "142,948",
        "youtubeID": "KGn-erOG-Bs"
    },
    {
        "ranking": "18",
        "title": "PASSO BEM SOLTO (Slowed)",
        "artist": "ATLXS",
        "image": "https://i.ytimg.com/vi/NT4eF9YsYnM/default.jpg",
        "prev": "11",
        "streak": "16",
        "streams": "140,765",
        "youtubeID": "NT4eF9YsYnM"
    },
    {
        "ranking": "19",
        "title": "Soda Pop",
        "artist": "Saja Boys & Andrew Choi & Neckwav & Danny Chung & KEVIN WOO & samUIL Lee & KPop Demon Hunters Cast",
        "image": "https://lh3.googleusercontent.com/ogvvJ4j4vEP1XxsfAJ1wZs-O7dRUe_9Ek_8ui-A9QZ59WaNhB4DPaND_SCsa3uYb6Wq3N69w8mJOF7oE=w180-h180-l90-rj",
        "prev": "45",
        "streak": "2",
        "streams": "134,730",
        "youtubeID": "983bBbJx0Mk"
    },
    {
        "ranking": "20",
        "title": "Raanjhan",
        "artist": "Parampara Thakur",
        "image": "https://lh3.googleusercontent.com/HDxRWaagMWwCIkzB4Fo-WCTWvdiO4e_RJ2cw7WLaizqVCCh58hYL9dXnkKBdkLVj11ydoN9mtguJTSxZ=w180-h180-l90-rj",
        "prev": "20",
        "streak": "37",
        "streams": "128,081",
        "youtubeID": "lBvbNxiVmZA"
    },
    {
        "ranking": "21",
        "title": "سكابا",
        "artist": "akhras",
        "image": "https://lh3.googleusercontent.com/lk1w-6b3zzvdWM10lHFFt5G6-wIHgd9LUC2-gloj0V6vPUXpHGMDzUat_UrZk4_A4RvaSzLx4KZ7JnMT=w180-h180-l90-rj",
        "prev": "23",
        "streak": "11",
        "streams": "118,006",
        "youtubeID": "Tv4--ekFMKQ"
    },
    {
        "ranking": "22",
        "title": "ما تقلقش",
        "artist": "Amr Diab",
        "image": "https://lh3.googleusercontent.com/h0kdl-YLc1Cv1433qTa76P_LC9hIeWo6B2styg7DeurhZhYWFUOl9bMboKnMWOJ8Ss8rxcX1TP9xK5k=w180-h180-l90-rj",
        "prev": "-",
        "streak": "1",
        "streams": "114,582",
        "youtubeID": "Hqw5Cd9_8tw"
    },
    {
        "ranking": "23",
        "title": "بتمنى أنساك",
        "artist": "Sherine",
        "image": "https://i.ytimg.com/vi/wEesaFi2YXA/default.jpg",
        "prev": "16",
        "streak": "8",
        "streams": "113,399",
        "youtubeID": "wEesaFi2YXA"
    },
    {
        "ranking": "24",
        "title": "Shake It To The Max (FLY) (Remix)",
        "artist": "Moliy & Silent Addy & Skillibeng & Shenseea",
        "image": "https://lh3.googleusercontent.com/nnD2FHAu-JyCYgXAVrcJG9SvTbguS8a37nN7-mYvtXYt1gTPOs8zB6R22q8_4ygpSsnIRo5mzfdW0TE=w180-h180-l90-rj",
        "prev": "19",
        "streak": "9",
        "streams": "110,399",
        "youtubeID": "UjBhbMMgLzc"
    },
    {
        "ranking": "25",
        "title": "اول مرة",
        "artist": "حمزة المحمداوي",
        "image": "https://lh3.googleusercontent.com/1YGONJetniUxD51eaJo8eSDdzvBuZm4SZ3kmrftBPdzs-4vcGqC9oniRQY6Vh70zMA46wIhC6alNugJl=w180-h180-l90-rj",
        "prev": "27",
        "streak": "38",
        "streams": "109,315",
        "youtubeID": "ETPU2RY_aCY"
    },
    {
        "ranking": "26",
        "title": "Khalbinnakame",
        "artist": "Mohammad Maqbool Mansoor",
        "image": "https://lh3.googleusercontent.com/lGSgYcok-suf9nhMWy1-5Cfiq6_tTHgQSdC6PJbFxkC8b2cRgpDwINYawCbdlAaUGM4fyAwXekukBP0=w180-h180-l90-rj",
        "prev": "21",
        "streak": "10",
        "streams": "108,081",
        "youtubeID": "fBve4qWA8Go"
    },
    {
        "ranking": "27",
        "title": "Ramayana (The Introduction Theme)",
        "artist": "Hans Zimmer & A. R. Rahman & Kumar Vishwas",
        "image": "https://lh3.googleusercontent.com/VU4E8EzMNfd-8m5GBlSIeUW8IljblK487kUStWLQodZ9rWSBgNb1CWS434NOOBx3Zpnpj9uHsFCsYGiq=w180-h180-l90-rj",
        "prev": "-",
        "streak": "1",
        "streams": "105,987",
        "youtubeID": "gzUu-FJ7s-Y"
    },
    {
        "ranking": "28",
        "title": "ناري",
        "artist": "Ahmad Sattar",
        "image": "https://lh3.googleusercontent.com/iIubt1COHhpDOCfIG6NE4Nql0Nn_pMYIgox_JAgxMosZ307hRpQJ2r7pTEi753tTn4XA47s8II2fQ2o=w180-h180-l90-rj",
        "prev": "29",
        "streak": "27",
        "streams": "103,876",
        "youtubeID": "tIWr1MO3uVo"
    },
    {
        "ranking": "29",
        "title": "THATTATHIL",
        "artist": "Sreehari K Nair",
        "image": "https://lh3.googleusercontent.com/zGVz0GvOFmtzuWP3gAqSUSh1IVWjU0lfh6mNvdg-NF4SCesXkX4HOk1UNnxb67KvDTJg0veJu_YpP-k=w180-h180-l90-rj",
        "prev": "26",
        "streak": "17",
        "streams": "103,070",
        "youtubeID": "DjLuN0DDb2s"
    },
    {
        "ranking": "30",
        "title": "الحب و بس",
        "artist": "Fadel Chaker",
        "image": "https://lh3.googleusercontent.com/k7prjHi63BZ0Zv2CL59UmILliSZUiZhQTDy4BOAyoB7jJZFT6ASiBiAJeTgrlkpAKDVQwYlxItpvsbg=w180-h180-l90-rj",
        "prev": "35",
        "streak": "4",
        "streams": "99,284",
        "youtubeID": "15f9PRTghDs"
    },
    {
        "ranking": "31",
        "title": "Dame Un Grrr",
        "artist": "Fantomel & Kate Linn",
        "image": "https://lh3.googleusercontent.com/wGrFmrL-ipWDpUyGQ7IbyN3hPgSMlx-M1FJDvZV0ecjGJQDWpVzdN1eeferHjBsHChXHrjyofHQ9Hi87=w180-h180-l90-rj",
        "prev": "33",
        "streak": "3",
        "streams": "98,165",
        "youtubeID": "wHlAnhkLUvw"
    },
    {
        "ranking": "32",
        "title": "Baba",
        "artist": "Amr Diab",
        "image": "https://lh3.googleusercontent.com/h0kdl-YLc1Cv1433qTa76P_LC9hIeWo6B2styg7DeurhZhYWFUOl9bMboKnMWOJ8Ss8rxcX1TP9xK5k=w180-h180-l90-rj",
        "prev": "-",
        "streak": "1",
        "streams": "96,855",
        "youtubeID": "3knHALzEC7M"
    },
    {
        "ranking": "33",
        "title": "مالیش بدیل",
        "artist": "Amr Diab",
        "image": "https://lh3.googleusercontent.com/h0kdl-YLc1Cv1433qTa76P_LC9hIeWo6B2styg7DeurhZhYWFUOl9bMboKnMWOJ8Ss8rxcX1TP9xK5k=w180-h180-l90-rj",
        "prev": "-",
        "streak": "1",
        "streams": "96,832",
        "youtubeID": "2fgYrTBFPt4"
    },
    {
        "ranking": "34",
        "title": "Ebtadena",
        "artist": "Amr Diab",
        "image": "https://lh3.googleusercontent.com/h0kdl-YLc1Cv1433qTa76P_LC9hIeWo6B2styg7DeurhZhYWFUOl9bMboKnMWOJ8Ss8rxcX1TP9xK5k=w180-h180-l90-rj",
        "prev": "-",
        "streak": "1",
        "streams": "92,560",
        "youtubeID": "tJWeC-ueKfE"
    },
    {
        "ranking": "35",
        "title": "At Peace",
        "artist": "Karan Aujla & Ikky",
        "image": "https://lh3.googleusercontent.com/nmF6MF-U6Lj02AgLaHOmyAI9UXdTiUTdLNfBPw4FbEwVyUArX9KHmwYc36GoHb-RVIOrSyfl1CC6tQ=w180-h180-l90-rj",
        "prev": "15",
        "streak": "2",
        "streams": "91,852",
        "youtubeID": "jVVwYXV22zg"
    },
    {
        "ranking": "36",
        "title": "Hope Song",
        "artist": "Govind Vasantha & Kapil Kapilan & Anwar Ali",
        "image": "https://lh3.googleusercontent.com/Pg9_5WU7jVA25aQlim5gACOEtXte7qF1zoPVGucHAZ6HYkBo2VqJOGTK-3bgD4x6dZoqvw2W3Q38Mkru=w180-h180-l90-rj",
        "prev": "44",
        "streak": "5",
        "streams": "90,965",
        "youtubeID": "a0goLSCAcBw"
    },
    {
        "ranking": "37",
        "title": "DIA DELÍCIA",
        "artist": "Nakama & Mc Staff & ΣP",
        "image": "https://lh3.googleusercontent.com/hsxflCF--GIjXPmWDO7lssf4NSt4j__v1SwOPa_bvBH85H4_EePffX0vVDtcxMpCoeMC_UREWPeXSMiF=w180-h180-l90-rj",
        "prev": "25",
        "streak": "4",
        "streams": "90,688",
        "youtubeID": "2cnloO84LA0"
    },
    {
        "ranking": "38",
        "title": "Kanmanipoove",
        "artist": "Jakes Bejoy & M. G. Sreekumar",
        "image": "https://lh3.googleusercontent.com/BQxq5meFeWazoE3zw_WiDfdpCpvP4_uNqXJXUV4DTBeYIaWCFKKpShMe2UkvzDB9hvdwXYBXEXmjT-_C=w180-h180-l90-rj",
        "prev": "32",
        "streak": "13",
        "streams": "89,476",
        "youtubeID": "f3D7QVjso7M"
    },
    {
        "ranking": "39",
        "title": "JANE BHAYE JAM MAYA",
        "artist": "Durgesh Thapa",
        "image": "https://lh3.googleusercontent.com/HYx8JZL61ipAANTe4v2jnA_K8-CHdCvYXXDEwMNYuJpVIb8G6gW7cEfozOuFMQMqkt42lugQbXrinocF=w180-h180-l90-rj",
        "prev": "-",
        "streak": "1",
        "streams": "86,158",
        "youtubeID": "NfCLgB-oUYs"
    },
    {
        "ranking": "40",
        "title": "KALAMANTINA / كلمنتينا",
        "artist": "Saint Levant & Marwan Moussa",
        "image": "https://i.ytimg.com/vi/GJ6iWDK1sgI/default.jpg",
        "prev": "36",
        "streak": "11",
        "streams": "85,942",
        "youtubeID": "GJ6iWDK1sgI"
    },
    {
        "ranking": "41",
        "title": "OIIA OIIA (Spinning Cat)",
        "artist": "W&W",
        "image": "https://lh3.googleusercontent.com/wRXnopAgsh85kfPdMylCi6GpkBkN_K3S-tNykHNzuymh2uQ6FpiwRhocprvUazZRzaGSPbZbmsTNccBj=w180-h180-l90-rj",
        "prev": "41",
        "streak": "23",
        "streams": "85,727",
        "youtubeID": "IxX_QHay02M"
    },
    {
        "ranking": "42",
        "title": "Jinguchaa",
        "artist": "Vaishali Samant & Shakthisree Gopalan & Adithya RK",
        "image": "https://lh3.googleusercontent.com/HPvio4r6y_JI6mmEWaKmLz757oXlN690Ar8ZGQ38o36A4wtPZnRA002RR8Cqtw2FUiyDlpxtZvGKynx8=w180-h180-l90-rj",
        "prev": "31",
        "streak": "12",
        "streams": "81,490",
        "youtubeID": "o9mivPpQlSA"
    },
    {
        "ranking": "43",
        "title": "الله يخلي الريس",
        "artist": "3mooriofficial",
        "image": "https://lh3.googleusercontent.com/gWU5xRIlbjcTaPVEVPxtDG4EEczQ1aykQbX1PRpjek_7hickRi8LZ5V-aYmf_N6q1rwfVNnWe1nV_AQQ=w180-h180-l90-rj",
        "prev": "50",
        "streak": "3",
        "streams": "79,972",
        "youtubeID": "Oi_tvt8HviQ"
    },
    {
        "ranking": "44",
        "title": "Saiyaara",
        "artist": "Faheem Abdullah & Arslan Nizami & Irshad Kamil",
        "image": "https://lh3.googleusercontent.com/0lPp5SGRnGUn0NWQvBCIONNZVe7T4PTtgvFSg9Tqx3UHUjqu0-DpqC-kpSApkwa04gdi-7nhW5nSmj06cQ=w180-h180-l90-rj",
        "prev": "86",
        "streak": "3",
        "streams": "79,185",
        "youtubeID": "BSJa1UytM8w"
    },
    {
        "ranking": "45",
        "title": "Kanimaa",
        "artist": "Santhosh Narayanan & The Indian Choral Ensemble",
        "image": "https://lh3.googleusercontent.com/tiSgfcvmkq-snCqGA-HMXwsmvBujbMbreF-hyqlNAusC378SNEFD7W9LeyYGsVT5AhXvhDMWI0Oq2mV3=w180-h180-l90-rj",
        "prev": "34",
        "streak": "16",
        "streams": "77,838",
        "youtubeID": "yG2MoXdFB34"
    },
    {
        "ranking": "46",
        "title": "كله مني",
        "artist": "Ali Kakooli",
        "image": "https://lh3.googleusercontent.com/MAXpvvg-ww6GwYQHdPjwN30oZDCXdiD86gUOfOJlT_TPfdFffzPf9T-37P3uXSeU8pACTaRnyrt9WOK0=w180-h180-l90-rj",
        "prev": "42",
        "streak": "7",
        "streams": "75,178",
        "youtubeID": "bxGOWchr6p8"
    },
    {
        "ranking": "47",
        "title": "عين وْهِدَبْ",
        "artist": "Abdul Majeed Abdullah",
        "image": "https://lh3.googleusercontent.com/GfVujALa91p5ATyyAmfCvK5PwyYgthNAFYHNDZaKklqN4zQsj5Bbnw3q9GAMqTgsFm1oAC7RmXu-6yJE=w180-h180-l90-rj",
        "prev": "-",
        "streak": "1",
        "streams": "75,078",
        "youtubeID": "ch-iQp3r9b8"
    },
    {
        "ranking": "48",
        "title": "Сигма Бой",
        "artist": "Betsy & Мария Янковская",
        "image": "https://lh3.googleusercontent.com/KNSkF4MOf_RraSi9JBwQ21uGM-PQ3L1mBhL-KhDCrDfJ5-tPAwWG-KER9ruxO-Hj8Ka3ocbPXEUWKnFt=w180-h180-l90-rj",
        "prev": "28",
        "streak": "29",
        "streams": "74,877",
        "youtubeID": "ueNY30Cs8Lk"
    },
    {
        "ranking": "49",
        "title": "Munthirichar (feat. Lil PAYYAN & SA)",
        "artist": "M.H.R & JOKER390P",
        "image": "https://lh3.googleusercontent.com/kPslTgg9weQYl7gheyKOy4uql-QZv-c_RO-sqiV7NClCYFm22DROhslEbSeg8xVqDYMA_tu9Emx_xcY=w180-h180-l90-rj",
        "prev": "43",
        "streak": "14",
        "streams": "74,245",
        "youtubeID": "32ZvuoWuqdM"
    },
    {
        "ranking": "50",
        "title": "Qatal",
        "artist": "Guru Randhawa & Sanjoy & Gill Machhrai",
        "image": "https://lh3.googleusercontent.com/ol9dqSKQMPPDelpJ4Kt5ay6oN8NYicQsZSeM-WpJdzpp8fWZ6Zv5lH1b2qZIdB9hZMCeuKsA4PEGErvp=w180-h180-l90-rj",
        "prev": "37",
        "streak": "11",
        "streams": "73,639",
        "youtubeID": "c-FKlE3_kHo"
    },
    {
        "ranking": "51",
        "title": "Chicken Banana",
        "artist": "Crazy Music Channel",
        "image": "https://lh3.googleusercontent.com/DPQTtiDIouQfy9RJhUHpTOKPBblJfB_lhgnnhpZbhKYOhh0uXo6ygBliA_iTdMbIFa1jCbdVsxlEGWfuQg=w180-h180-l90-rj",
        "prev": "38",
        "streak": "15",
        "streams": "72,024",
        "youtubeID": "ig7EKb6BrQk"
    },
    {
        "ranking": "52",
        "title": "Kejah",
        "artist": "MBL_ & AYARKAY",
        "image": "https://lh3.googleusercontent.com/Tawfhm-TfWfIjWP0O6dc5m7_ibWuCRCPMPMlviLPqlC_vqNgiF1_e-Jf_846uRXjOqWI66Cfxx-qYMI=w180-h180-l90-rj",
        "prev": "52",
        "streak": "4",
        "streams": "66,871",
        "youtubeID": "BCqPRnjfotk"
    },
    {
        "ranking": "53",
        "title": "Shaif Amar",
        "artist": "Amr Diab",
        "image": "https://lh3.googleusercontent.com/h0kdl-YLc1Cv1433qTa76P_LC9hIeWo6B2styg7DeurhZhYWFUOl9bMboKnMWOJ8Ss8rxcX1TP9xK5k=w180-h180-l90-rj",
        "prev": "-",
        "streak": "1",
        "streams": "66,737",
        "youtubeID": "yZvYROJvsHg"
    },
    {
        "ranking": "54",
        "title": "Onam Mood",
        "artist": "Fejo & Himna Hilari & Hinitha Hilary",
        "image": "https://lh3.googleusercontent.com/775Z9hKxbsV9DvPm_oN9uF9emUha_S0_4hGYlPNkEbRrydlDrECQGHnmFSLDtdbn6Yhe1KKxzQnRR6M=w180-h180-l90-rj",
        "prev": "-",
        "streak": "1",
        "streams": "66,414",
        "youtubeID": "GJZAcj4P99g"
    },
    {
        "ranking": "55",
        "title": "Nasha",
        "artist": "Jasmine Sandlas & Sachet Tandon & Divya Kumar & Sumonto Mukherjee",
        "image": "https://lh3.googleusercontent.com/q1P_Mhzu91HmxkLEqGaTtpm_piTXFyxMcUqEfSIxShBz0a_CvCTFTCyxLnRttwi91-_Liw05Jzv4We_guQ=w180-h180-l90-rj",
        "prev": "51",
        "streak": "13",
        "streams": "63,596",
        "youtubeID": "QPSAjqjylTc"
    },
    {
        "ranking": "56",
        "title": "إشارات",
        "artist": "Amr Diab",
        "image": "https://lh3.googleusercontent.com/h0kdl-YLc1Cv1433qTa76P_LC9hIeWo6B2styg7DeurhZhYWFUOl9bMboKnMWOJ8Ss8rxcX1TP9xK5k=w180-h180-l90-rj",
        "prev": "-",
        "streak": "1",
        "streams": "61,246",
        "youtubeID": "tgpsl697dN8"
    },
    {
        "ranking": "57",
        "title": "Habibty Malak",
        "artist": "Amr Diab",
        "image": "https://lh3.googleusercontent.com/h0kdl-YLc1Cv1433qTa76P_LC9hIeWo6B2styg7DeurhZhYWFUOl9bMboKnMWOJ8Ss8rxcX1TP9xK5k=w180-h180-l90-rj",
        "prev": "-",
        "streak": "1",
        "streams": "60,151",
        "youtubeID": "CIuagRrEcPw"
    },
    {
        "ranking": "58",
        "title": "Gabriela",
        "artist": "KATSEYE",
        "image": "https://lh3.googleusercontent.com/Boy9TIypluE9O8sPJO_lM_ldzEi22070TzsJDoB4TkhXUzDsneRqhjWTRVtBSrDHwuw4afG6GdAd46LHSQ=w180-h180-l90-rj",
        "prev": "59",
        "streak": "3",
        "streams": "60,111",
        "youtubeID": "CjnB56tSCQI"
    },
    {
        "ranking": "59",
        "title": "Koka Gaani",
        "artist": "Ranjit Bawa & Bunty Bains & Desi Crew",
        "image": "https://lh3.googleusercontent.com/0PsIQR7BDehrdF2EaZcOBz_9jIdJkvZSBf7KG-D6lg24FH2Jpbs59nsG5wNr34vO6sNaxSFpT1oMwxme9Q=w180-h180-l90-rj",
        "prev": "-",
        "streak": "1",
        "streams": "60,107",
        "youtubeID": "6kBkiENmCag"
    },
    {
        "ranking": "60",
        "title": "Pretty Little Baby",
        "artist": "Connie Francis",
        "image": "https://lh3.googleusercontent.com/kZv2QsDzRtrfpPS2JR7zUSJqqGdBf-8CFgKLaD_ZSAQO45Kgcs2cZNJ5HVYuo0V-Wk3Y96KfUQDWEXDu=w180-h180-l90-rj",
        "prev": "48",
        "streak": "8",
        "streams": "60,086",
        "youtubeID": "A1MdThqGarI"
    },
    {
        "ranking": "61",
        "title": "Supreme",
        "artist": "Shubh",
        "image": "https://lh3.googleusercontent.com/zuzIKOBT1migLpcsVfZCyFIm_4JrkMY8HSftUCArWN8i6PHr2Gz9DLKIx-UHLqMbTCrzpY6ufdnsP7s=w180-h180-l90-rj",
        "prev": "58",
        "streak": "12",
        "streams": "59,807",
        "youtubeID": "AX1zRInC_TA"
    },
    {
        "ranking": "62",
        "title": "Sajde",
        "artist": "Faheem Abdullah & Huzaif Nazar",
        "image": "https://lh3.googleusercontent.com/RifEUhIwW91Kp-cOz7-5xJfkRswdYtsJb_oMtKx7gLP0-9eztF8TTcLBGJRmEfj8X3T_Upe7ASoE5ejHGg=w180-h180-l90-rj",
        "prev": "78",
        "streak": "12",
        "streams": "59,082",
        "youtubeID": "t9dUiCYJpiw"
    },
    {
        "ranking": "63",
        "title": "Lose My Mind (feat. Doja Cat)",
        "artist": "Don Toliver",
        "image": "https://lh3.googleusercontent.com/zWZlQ2r1uoayrYrZzZvfFDtB1885rk00g9kmFlGu8Rxdm6ngcdWbZis67xAIed3X0X5Nu6WObh6WQZK_rA=w180-h180-l90-rj",
        "prev": "-",
        "streak": "1",
        "streams": "58,939",
        "youtubeID": "WWEs82u37Mw"
    },
    {
        "ranking": "64",
        "title": "Jhim Jhim",
        "artist": "Ekdev Limbu & Neha Kakkar & Rajat Nagpal & Rana Sotal",
        "image": "https://lh3.googleusercontent.com/XTV6HvNOylns8WbcMKnjWviNlC56UVJait-XKcosKFJ6TzqhxLUeQcB9Y97Ea-3vftoko-RvH2gZNVxj=w180-h180-l90-rj",
        "prev": "22",
        "streak": "2",
        "streams": "58,833",
        "youtubeID": "ZLU4rx24024"
    },
    {
        "ranking": "65",
        "title": "Vaada Veda",
        "artist": "Vedan & Jakes Bejoy",
        "image": "https://lh3.googleusercontent.com/jqaf1ZfwieMNoFwV9PBm1nNSUoByTb5bN-LM2lGM7fQl3azrh1znn4TUCjAilzcQA0smr9FBkKRYvw6-WQ=w180-h180-l90-rj",
        "prev": "57",
        "streak": "7",
        "streams": "58,460",
        "youtubeID": "SRsSnffB4p0"
    },
    {
        "ranking": "66",
        "title": "هوى الجنوب",
        "artist": "Fadel Chaker",
        "image": "https://lh3.googleusercontent.com/-ii1JzoQ-29NRqb_eeMCu5hmbPnuQTRdPpJCxHI9cdXv6FSHpW0Pi-cUy5NEJxRW8hzVTE1txNKobFM=w180-h180-l90-rj",
        "prev": "80",
        "streak": "14",
        "streams": "57,944",
        "youtubeID": "qtmCCy-sc8g"
    },
    {
        "ranking": "67",
        "title": "Tere Bina",
        "artist": "A. R. Rahman & Chinmayi & Murtuza Khan & Qadir Khan",
        "image": "https://lh3.googleusercontent.com/x-S2zkffDNM5MlgF8twdjL2SDCnbxkFAexaKpE2-fGnGmY07jPIOyCtUbjT1HPUf6mLURYAqc2dLV_4P=w180-h180-l90-rj",
        "prev": "73",
        "streak": "9",
        "streams": "57,633",
        "youtubeID": "9JDSGhhiOwI"
    },
    {
        "ranking": "68",
        "title": "Ordinary",
        "artist": "Alex Warren",
        "image": "https://lh3.googleusercontent.com/IpMxcpbAoa3Dh09aQj6lvQtXpVd7B7C7dEF6SrGY9t_Hxs5xo7lFFJGXNyi1Ts3iNwnlxhGBmWjVn0QF=w180-h180-l90-rj",
        "prev": "62",
        "streak": "11",
        "streams": "57,150",
        "youtubeID": "u2ah9tWTkmk"
    },
    {
        "ranking": "69",
        "title": "ھلونھم",
        "artist": "Amr Diab",
        "image": "https://lh3.googleusercontent.com/h0kdl-YLc1Cv1433qTa76P_LC9hIeWo6B2styg7DeurhZhYWFUOl9bMboKnMWOJ8Ss8rxcX1TP9xK5k=w180-h180-l90-rj",
        "prev": "-",
        "streak": "1",
        "streams": "57,104",
        "youtubeID": "iSaWqu8ipU0"
    },
    {
        "ranking": "70",
        "title": "LUNA BALA (Slowed)",
        "artist": "Yb Wasg'ood & Ariis",
        "image": "https://i.ytimg.com/vi/dukNdSgaLtc/default.jpg",
        "prev": "39",
        "streak": "9",
        "streams": "56,968",
        "youtubeID": "dukNdSgaLtc"
    },
    {
        "ranking": "71",
        "title": "حفلة تنكرية",
        "artist": "Rahma Mohsen",
        "image": "https://lh3.googleusercontent.com/qFCRfwiCr9s_miQyyGZV05CYwMuj1HbSR3qdRs0FCfqQClWUWeq_NAyswVcunFImthJZQBqcAvK18sWS=w180-h180-l90-rj",
        "prev": "67",
        "streak": "17",
        "streams": "55,840",
        "youtubeID": "amyJSfeUvvY"
    },
    {
        "ranking": "72",
        "title": "Behuli",
        "artist": "Sajjan Raj Vaidya",
        "image": "https://lh3.googleusercontent.com/B35ucuM_duOFDu_EJMiNJPION0OhjDXdEfX_77TOPfqEUTi5QfZsHaHBj0XewrQ0E6yRNLELtff7bUw=w180-h180-l90-rj",
        "prev": "-",
        "streak": "1",
        "streams": "55,234",
        "youtubeID": "WUfeSOe1PJ4"
    },
    {
        "ranking": "73",
        "title": "المطافي",
        "artist": "مشعل شايع",
        "image": "https://lh3.googleusercontent.com/GT74kg9jPEgOeGRussuZrJS2GgrxW8ZSGnctq7QQXj5Vu8YKBw3Hds5-WbFmXFORvwdIKNpw3SDS6U9c=w180-h180-l90-rj",
        "prev": "66",
        "streak": "9",
        "streams": "54,311",
        "youtubeID": "N9vwK7FWkYo"
    },
    {
        "ranking": "74",
        "title": "Dum Dum",
        "artist": "Jaani & Bunny & Asees Kaur",
        "image": "https://lh3.googleusercontent.com/zeouULo0nKBym8Qn1GvZkxyzvPLoG_3-gzTAP5qQ4C6B9mWUFb1cBnjivv06l6QWNBREwo-C15TMRvwW=w180-h180-l90-rj",
        "prev": "89",
        "streak": "2",
        "streams": "54,154",
        "youtubeID": "sd1XTaoYTl4"
    },
    {
        "ranking": "75",
        "title": "MONTAGEM TOMADA (Slowed)",
        "artist": "MXZI",
        "image": "https://i.ytimg.com/vi/qN_ecsamhms/default.jpg",
        "prev": "53",
        "streak": "14",
        "streams": "53,477",
        "youtubeID": "qN_ecsamhms"
    },
    {
        "ranking": "76",
        "title": "CHAL",
        "artist": "Dabzee & Rishi Roy & Fathima Jahaan",
        "image": "https://i.ytimg.com/vi/aD9snLyynzM/default.jpg",
        "prev": "65",
        "streak": "15",
        "streams": "52,108",
        "youtubeID": "aD9snLyynzM"
    },
    {
        "ranking": "77",
        "title": "وغلبني",
        "artist": "Fadel Chaker",
        "image": "https://lh3.googleusercontent.com/IYz9s9GdxU-1wPk8eFFWZCLk7bAuDx2xOCgq-LkodNCBpM3kJrGusbrA_KKhXkrn2O8oSfKazRuDkUQ=w180-h180-l90-rj",
        "prev": "91",
        "streak": "8",
        "streams": "52,097",
        "youtubeID": "GUYKNXvwHaM"
    },
    {
        "ranking": "78",
        "title": "Камин",
        "artist": "EMIN & JONY",
        "image": "https://lh3.googleusercontent.com/Jd-9NfX7fygj3rF55Alsl1d-SMcZW8s0fW12Dokel_gSkdIRV1Jcz_6ag5eyuhM-l1Rrp8yD3hoa7DxD=w180-h180-l90-rj",
        "prev": "63",
        "streak": "4",
        "streams": "51,908",
        "youtubeID": "6SEr1XcZG4M"
    },
    {
        "ranking": "79",
        "title": "Sohna Sohni (feat. Gurlez Akhtar)",
        "artist": "SABBA",
        "image": "https://lh3.googleusercontent.com/rv90CW7wdpA4TxHPaDvk93tdkyY6rj0AtKCyBnbSJke9kHoVIRLlQUezzBIY-OijtzH7hjNSpee3vU16bw=w180-h180-l90-rj",
        "prev": "-",
        "streak": "1",
        "streams": "50,983",
        "youtubeID": "-FPIV-z9GR0"
    },
    {
        "ranking": "80",
        "title": "Hawaiian Roller Coaster Ride",
        "artist": "Iam Tongi & Kamehameha Schools Children's Chorus",
        "image": "https://lh3.googleusercontent.com/pxXvNYPi-pU3wp0tJhlYpP3Hask5zkLGkhkoczRUHxbcagK6VgySbTCQnanZcHnsePKt-Z_cn_yVgrsk=w180-h180-l90-rj",
        "prev": "60",
        "streak": "7",
        "streams": "50,315",
        "youtubeID": "kXB-Ibr55LI"
    },
    {
        "ranking": "81",
        "title": "Kadha Thudarum (Timeless Bond)",
        "artist": "Jakes Bejoy & Hariharan & Gokul Gopakumar & Mohanlal",
        "image": "https://lh3.googleusercontent.com/jPiGO8pK22O2610UyqittbsC9_aUQwRXnJMwBD3Qyg-v5twI9Fc5a3GSkuEFyoCR3aMysFHpMa5gA7g9=w180-h180-l90-rj",
        "prev": "69",
        "streak": "12",
        "streams": "49,687",
        "youtubeID": "iBVxogg5QwE"
    },
    {
        "ranking": "82",
        "title": "SHOES OFF",
        "artist": "Prem Dhillon & Iqbal",
        "image": "https://lh3.googleusercontent.com/3z5-UNDC_SXWlbXEnVMET_knNAbkOgc5oCdurOudSDlZ_FL18AcIgsKDJ7cORMrL9herm-YDgv3TdeM=w180-h180-l90-rj",
        "prev": "-",
        "streak": "1",
        "streams": "49,445",
        "youtubeID": "Gu_rNg4gZzQ"
    },
    {
        "ranking": "83",
        "title": "یا بخته",
        "artist": "Amr Diab",
        "image": "https://lh3.googleusercontent.com/h0kdl-YLc1Cv1433qTa76P_LC9hIeWo6B2styg7DeurhZhYWFUOl9bMboKnMWOJ8Ss8rxcX1TP9xK5k=w180-h180-l90-rj",
        "prev": "-",
        "streak": "1",
        "streams": "48,935",
        "youtubeID": "EHDb_rId3PE"
    },
    {
        "ranking": "84",
        "title": "Your Idol",
        "artist": "Saja Boys & Andrew Choi & Neckwav &  & KEVIN WOO & samUIL Lee & KPop Demon Hunters Cast",
        "image": "https://lh3.googleusercontent.com/ogvvJ4j4vEP1XxsfAJ1wZs-O7dRUe_9Ek_8ui-A9QZ59WaNhB4DPaND_SCsa3uYb6Wq3N69w8mJOF7oE=w180-h180-l90-rj",
        "prev": "81",
        "streak": "2",
        "streams": "48,331",
        "youtubeID": "5QIQ5QHqDbw"
    },
    {
        "ranking": "85",
        "title": "Gnarly",
        "artist": "KATSEYE",
        "image": "https://lh3.googleusercontent.com/S62UcAT1BnwwUlAltPiPeElmnEiyQvq764YP0MjJJRCLIsiNZjO5NNHdNt-Tb6rCeRtW4-vNq2UOWeQ=w180-h180-l90-rj",
        "prev": "71",
        "streak": "10",
        "streams": "48,071",
        "youtubeID": "R2-yomhYAj4"
    },
    {
        "ranking": "86",
        "title": "Sumahaasithe",
        "artist": "Sachin Balu",
        "image": "https://lh3.googleusercontent.com/TuTLfYkMgvEbTutHohvZElQF1oPsWR6etgmDNV03hBa1Cycc0FzAgVeTBgLR5XkIwrIze6sP6jsEq5s=w180-h180-l90-rj",
        "prev": "68",
        "streak": "7",
        "streams": "47,615",
        "youtubeID": "NG7Y484M7Cc"
    },
    {
        "ranking": "87",
        "title": "Starboy (feat. Daft Punk)",
        "artist": "The Weeknd",
        "image": "https://lh3.googleusercontent.com/dcxXIIlest09vnvKznWM9VWQXu1EL7lKxBzXGzwgmVjmMNBm1dEWT_0qn1xrEZYyKF_qRE1TLq8P_JY_mQ=w180-h180-l90-rj",
        "prev": "-",
        "streak": "47",
        "streams": "47,459",
        "youtubeID": "34Na4j8AVgA"
    },
    {
        "ranking": "88",
        "title": "يا غايب عن عيني",
        "artist": "Mehad Hamad",
        "image": "https://lh3.googleusercontent.com/wsPHmCt_d3mhTFE7jRxl1edrMfU0DMidfw0NAzpUTRh_AyUWnhLgz_sO42nLPQAaNNyDU3rofM2zIrYT=w180-h180-l90-rj",
        "prev": "90",
        "streak": "19",
        "streams": "46,407",
        "youtubeID": "JnbU-QqyMJA"
    },
    {
        "ranking": "89",
        "title": "Free",
        "artist": "Rumi & Jinu & EJAE & Andrew Choi & KPop Demon Hunters Cast",
        "image": "https://lh3.googleusercontent.com/ogvvJ4j4vEP1XxsfAJ1wZs-O7dRUe_9Ek_8ui-A9QZ59WaNhB4DPaND_SCsa3uYb6Wq3N69w8mJOF7oE=w180-h180-l90-rj",
        "prev": "-",
        "streak": "1",
        "streams": "46,350",
        "youtubeID": "fjOeJssZX_Q"
    },
    {
        "ranking": "90",
        "title": "हरनवे धई धई दबाता",
        "artist": "Samar Singh & Neha Raj",
        "image": "https://lh3.googleusercontent.com/bVQTRC4yD5YguK-aJY4DeFexg9smyTZRp14qS0xaOl3XhiTcewr7gjB-nU5yumtWoYvVZXGacbaEsrdc=w180-h180-l90-rj",
        "prev": "-",
        "streak": "1",
        "streams": "46,006",
        "youtubeID": "cssY0jENfoc"
    },
    {
        "ranking": "91",
        "title": "نركب هالسيارة",
        "artist": "Abu Ward",
        "image": "https://lh3.googleusercontent.com/rtWsp_XIxCCyigZOCXqvDGUg5hI8UGQGGGtPPhEdMQS2Ay_ftnkoan_dKsQ5IpHYEFJi990KSllIQ7xNRw=w180-h180-l90-rj",
        "prev": "-",
        "streak": "1",
        "streams": "45,527",
        "youtubeID": "y6w8wcE2QK0"
    },
    {
        "ranking": "92",
        "title": "LABUBU FUNK",
        "artist": "SXLLX",
        "image": "https://i.ytimg.com/vi/gb0_LhNRe4Q/default.jpg",
        "prev": "46",
        "streak": "3",
        "streams": "45,432",
        "youtubeID": "gb0_LhNRe4Q"
    },
    {
        "ranking": "93",
        "title": "یلا (feat. Abdallah Diab)",
        "artist": "Amr Diab",
        "image": "https://lh3.googleusercontent.com/h0kdl-YLc1Cv1433qTa76P_LC9hIeWo6B2styg7DeurhZhYWFUOl9bMboKnMWOJ8Ss8rxcX1TP9xK5k=w180-h180-l90-rj",
        "prev": "-",
        "streak": "1",
        "streams": "44,666",
        "youtubeID": "eZNqpkXYC3Y"
    },
    {
        "ranking": "94",
        "title": "Dhun",
        "artist": "Arijit Singh & Mithoon",
        "image": "https://lh3.googleusercontent.com/LbSZO8GtotJrdk49H0xQuB7rZD2DpdyJO_it31_XrQ_AMdoKG67VDS33JgZjn02f4C6kOgtvc8S4dfUR=w180-h180-l90-rj",
        "prev": "-",
        "streak": "1",
        "streams": "44,152",
        "youtubeID": "cUmUOb7j3dc"
    },
    {
        "ranking": "95",
        "title": "Rock That Body",
        "artist": "Black Eyed Peas",
        "image": "https://lh3.googleusercontent.com/XR-7iPvWDmouM1SR4zzzlRa8m-r_Ck_eyyHfyMRL-0-NjS8Sy-eotVXERmnYnhyTc9Du1MPmt6Y67dom8w=w180-h180-l90-rj",
        "prev": "85",
        "streak": "2",
        "streams": "44,123",
        "youtubeID": "nmnjL26OBcY"
    },
    {
        "ranking": "96",
        "title": "Besos (feat. Karl Wine)",
        "artist": "Shreya Ghoshal & Rajat Nagpal & Freebot",
        "image": "https://lh3.googleusercontent.com/2ro6J3PLEx5cAgMOV3UNo8GKeXhaSkcWcfQx7y3RIw-9n7fUntrPKNZrrxIlO4q02Pk6ScGuNFc1RRJAZw=w180-h180-l90-rj",
        "prev": "87",
        "streak": "9",
        "streams": "43,034",
        "youtubeID": "U3vONIizYG8"
    },
    {
        "ranking": "97",
        "title": "Brainrot Rap",
        "artist": "Party Tunes",
        "image": "https://lh3.googleusercontent.com/cWHZ-z13HQKgI_fb_BVjIZ91CrtSqiF1UQat3FlX0vgJY89fwAEiMHqtIuV958TM4XLSCFEAptZrQteY=w180-h180-l90-rj",
        "prev": "64",
        "streak": "4",
        "streams": "42,955",
        "youtubeID": "T_NKi5KHUdI"
    },
    {
        "ranking": "98",
        "title": "Courtside",
        "artist": "Karan Aujla & Signature By Sb",
        "image": "https://lh3.googleusercontent.com/5cqb_FFeAPbzvatQ5WU8DQMsa6YZcDrFElVDXp-qJLI9mKt8un_JB1iT7moGJlnK3_0Zuelt66hScpEz=w180-h180-l90-rj",
        "prev": "-",
        "streak": "8",
        "streams": "42,824",
        "youtubeID": "Z8IRRphKFZA"
    },
    {
        "ranking": "99",
        "title": "like JENNIE",
        "artist": "JENNIE",
        "image": "https://lh3.googleusercontent.com/Z3gufPaLCcWuJNE4NH6KhlbUSrnx3hvUQgnhwQBrUDNzEgAp1aNMuCr0nv0gJxU8XcS2Rp9I-BHPZt_i=w180-h180-l90-rj",
        "prev": "84",
        "streak": "18",
        "streams": "42,789",
        "youtubeID": "JSFG-IE8n_c"
    },
    {
        "ranking": "100",
        "title": "Thuli Thuli",
        "artist": "Haricharan & Tanvi Shah",
        "image": "https://lh3.googleusercontent.com/t4Ua-J4dq7I9FQ8PtcoLECOm6jh6ub__KPdA0dijcBKgdcfvS3-hRp2B6OlZDaQCFiXi5sQ42Y9oYy9vHQ=w180-h180-l90-rj",
        "prev": "-",
        "streak": "4",
        "streams": "42,728",
        "youtubeID": "v-hL3sks2qI"
    }
]